mutwo/mbrola_converters/__init__.py
mutwo/mbrola_converters/mbrola.py
mutwo/mbrola_version/__init__.py
mutwo.mbrola-0.3.1.dist-info/LICENSE
mutwo.mbrola-0.3.1.dist-info/METADATA
mutwo.mbrola-0.3.1.dist-info/WHEEL
mutwo.mbrola-0.3.1.dist-info/top_level.txt
mutwo.mbrola-0.3.1.dist-info/RECORD
