Metadata-Version: 2.1
Name: mutwo.mbrola
Version: 0.3.1
Summary: mbrola extension for event based framework for generative art
Home-page: https://github.com/mutwo-org/mutwo.mbrola
Author: Levin Eric Zimmermann
Author-email: levin.eric.zimmermann@posteo.eu
License: GPL
Project-URL: Documentation, https://mutwo.readthedocs.io/en/latest/
Requires-Python: >=3.9, <4
License-File: LICENSE
Requires-Dist: mutwo.core (<1.00.0,>=0.61.4)
Requires-Dist: mutwo.music (<1.0.0,>=0.17.0)
Requires-Dist: voxpopuli (<1,>=0.3.7)
Provides-Extra: testing
Requires-Dist: nose ; extra == 'testing'
Requires-Dist: coveralls ; extra == 'testing'
Requires-Dist: sox (==1.4.1) ; extra == 'testing'
Requires-Dist: tensorflow (>=2.0.0) ; extra == 'testing'
Requires-Dist: crepe (==0.0.12) ; extra == 'testing'
